tzcodegen/__init__.py
tzcodegen/conf.py
tzcodegen/generator.py
tzcodegen/initialization.py
tzcodegen/utils.py
tzcodegen/stubs/Makefile
tzcodegen/stubs/authentic_execution.c
tzcodegen/stubs/authentic_execution.h
tzcodegen/stubs/connection.c
tzcodegen/stubs/connection.h
tzcodegen/stubs/crypto.c
tzcodegen/stubs/crypto.h
tzcodegen/stubs/import.c
tzcodegen/stubs/pta_attestation.h
tzcodegen/stubs/spongent.c
tzcodegen/stubs/spongent.h
tzcodegen/stubs/sub.mk
tzcodegen/stubs/ta.h
tzcodegen/stubs/user_ta_header_defines.h
tz_codegen-0.4.7.dist-info/LICENSE
tz_codegen-0.4.7.dist-info/METADATA
tz_codegen-0.4.7.dist-info/WHEEL
tz_codegen-0.4.7.dist-info/entry_points.txt
tz_codegen-0.4.7.dist-info/top_level.txt
tz_codegen-0.4.7.dist-info/RECORD
