Metadata-Version: 2.1
Name: tz-codegen
Version: 0.4.7
Summary: Trustzone module code generator for the Authentic Execution framework
Home-page: UNKNOWN
Author: Sepideh Pouyanrad
License: UNKNOWN
Platform: UNKNOWN
Classifier: Programming Language :: Python :: 3
Classifier: License :: OSI Approved :: MIT License
Classifier: Operating System :: POSIX :: Linux
Requires-Python: >=3.6
Requires-Dist: colorlog (==4.6.2)
